py_sysml_rdf/__init__.py
py_sysml_rdf/ontology_reader.py
py_sysml_rdf/sysml.py
py_sysml_rdf/sysml.ttl
py_sysml_rdf-0.0.3.dist-info/LICENSE
py_sysml_rdf-0.0.3.dist-info/METADATA
py_sysml_rdf-0.0.3.dist-info/WHEEL
py_sysml_rdf-0.0.3.dist-info/RECORD
